datefinder.py
datefinder-0.6.0.dist-info/DESCRIPTION.rst
datefinder-0.6.0.dist-info/METADATA
datefinder-0.6.0.dist-info/RECORD
datefinder-0.6.0.dist-info/WHEEL
datefinder-0.6.0.dist-info/metadata.json
datefinder-0.6.0.dist-info/top_level.txt
