Metadata-Version: 2.0
Name: datefinder
Version: 0.6.0
Summary: Extract datetime objects from strings
Home-page: https://github.com/akoumjian/datefinder
Author: Alec Koumjian
Author-email: akoumjian@gmail.com
License: MIT
Keywords: datetime parser nlp
Platform: UNKNOWN
Classifier: Development Status :: 3 - Alpha
Classifier: Intended Audience :: Developers
Classifier: License :: OSI Approved :: MIT License
Classifier: Programming Language :: Python :: 2
Classifier: Programming Language :: Python :: 2.7
Classifier: Programming Language :: Python :: 3
Classifier: Programming Language :: Python :: 3.3
Classifier: Programming Language :: Python :: 3.4
Classifier: Programming Language :: Python :: 3.5
Classifier: Natural Language :: English
Requires-Dist: dateparser
Requires-Dist: python-dateutil
Requires-Dist: regex
Provides-Extra: dev
Requires-Dist: mock; extra == 'dev'
Requires-Dist: pytest; extra == 'dev'
Provides-Extra: test
Requires-Dist: mock; extra == 'test'
Requires-Dist: pytest; extra == 'test'
